README.md
setup.py
ivan.egg-info/PKG-INFO
ivan.egg-info/SOURCES.txt
ivan.egg-info/dependency_links.txt
ivan.egg-info/top_level.txt
ivan.egg-info/zip-safe
ivan_test/__init__.py
ivan_test/app.py