Metadata-Version: 1.1
Name: ivan
Version: 0.1.1
Summary: test pip
Home-page: https://github.com/goupper/upload-oss-file
Author: ivan
Author-email: chongwuwy@163.com
License: MIT
Platform: UNKNOWN
Classifier: License :: OSI Approved :: MIT License
Classifier: Programming Language :: Python
Classifier: Intended Audience :: Developers
Classifier: Operating System :: OS Independent
